[{"char":"傾","on":"ケイ","kun":"かたむ(く)","romaji":"kei / katamu(ku)","meaning":"เอียง, แนวโน้ม","examples":[{"jp":"傾向があります。","romaji":"Keikou ga arimasu.","th":"มีแนวโน้ม"},{"jp":"傾斜が急です。","romaji":"Keisha ga kyuu desu.","th":"ความลาดชันสูง"},{"jp":"建物が傾いています。","romaji":"Tatemono ga katamuite imasu.","th":"ตึกเอียง"}]},{"char":"範","on":"ハン","kun":"—","romaji":"han","meaning":"ขอบเขต, ตัวอย่าง","examples":[{"jp":"範囲を確認します。","romaji":"Han'i o kakunin shimasu.","th":"ตรวจสอบขอบเขต"},{"jp":"模範になります。","romaji":"Mohan ni narimasu.","th":"เป็นแบบอย่าง"},{"jp":"規範を守ります。","romaji":"Kihan o mamorimasu.","th":"ปฏิบัติตามมาตรฐาน"}]},{"char":"握","on":"アク","kun":"にぎ(る)","romaji":"aku / nigi(ru)","meaning":"กำ, จับ","examples":[{"jp":"把握しています。","romaji":"Haaku shite imasu.","th":"เข้าใจสถานการณ์"},{"jp":"手を握りました。","romaji":"Te o nigirimashita.","th":"จับมือ"},{"jp":"握手をしましょう。","romaji":"Akushu o shimashou.","th":"จับมือกันเถอะ"}]},{"char":"貢","on":"コウ","kun":"—","romaji":"kou","meaning":"อุทิศ, ส่งบรรณาการ","examples":[{"jp":"貢献したいです。","romaji":"Kouken shitai desu.","th":"อยากทำประโยชน์"},{"jp":"社会貢献活動。","romaji":"Shakai kouken katsudou.","th":"กิจกรรมเพื่อสังคม"},{"jp":"大きく貢献しました。","romaji":"Ookiku kouken shimashita.","th":"มีส่วนช่วยอย่างมาก"}]},{"char":"達","on":"タツ","kun":"—","romaji":"tatsu","meaning":"ถึง, บรรลุ","examples":[{"jp":"目標を達成します。","romaji":"Mokuhyou o tassei shimasu.","th":"บรรลุเป้าหมาย"},{"jp":"友達と遊びます。","romaji":"Tomodachi to asobimasu.","th":"เล่นกับเพื่อน"},{"jp":"上達しました。","romaji":"Joutatsu shimashita.","th":"พัฒนาขึ้น"}]},{"char":"克","on":"コク","kun":"か(つ)","romaji":"koku / ka(tsu)","meaning":"เอาชนะ","examples":[{"jp":"困難を克服します。","romaji":"Konnan o kokufuku shimasu.","th":"เอาชนะอุปสรรค"},{"jp":"自己を克服する。","romaji":"Jiko o kokufuku suru.","th":"ก้าวข้ามตัวเอง"},{"jp":"克明に書きました。","romaji":"Kokumei ni kakimashita.","th":"เขียนละเอียด"}]},{"char":"曖","on":"アイ","kun":"—","romaji":"ai","meaning":"คลุมเครือ","examples":[{"jp":"曖昧な答えです。","romaji":"Aimai na kotae desu.","th":"เป็นคำตอบที่คลุมเครือ"},{"jp":"曖昧にしないで。","romaji":"Aimai ni shinaide.","th":"อย่ากำกวม"},{"jp":"曖昧な記憶。","romaji":"Aimai na kioku.","th":"ความทรงจำเลือนๆ"}]},{"char":"昧","on":"マイ","kun":"—","romaji":"mai","meaning":"มืดบอด, ไม่ชัด","examples":[{"jp":"曖昧です。","romaji":"Aimai desu.","th":"คลุมเครือ"},{"jp":"三昧に浸る。","romaji":"Zanmai ni hitaru.","th":"หมกมุ่น"},{"jp":"蒙昧な状態。","romaji":"Moumai na joutai.","th":"สภาพมืดมน"}]},{"char":"妥","on":"ダ","kun":"—","romaji":"da","meaning":"ประนีประนอม, เหมาะสม","examples":[{"jp":"妥協しません。","romaji":"Dakyou shimasen.","th":"ไม่ประนีประนอม"},{"jp":"妥当な判断です。","romaji":"Datou na handan desu.","th":"เป็นการตัดสินที่เหมาะสม"},{"jp":"妥結に至りました。","romaji":"Daketsu ni itarimashita.","th":"บรรลุข้อตกลง"}]},{"char":"矛","on":"ム","kun":"ほこ","romaji":"mu / hoko","meaning":"หอก, ขัดแย้ง","examples":[{"jp":"矛盾しています。","romaji":"Mujun shite imasu.","th":"ขัดแย้งกัน"},{"jp":"矛盾を感じる。","romaji":"Mujun o kanjiru.","th":"รู้สึกถึงความขัดแย้ง"},{"jp":"話に矛盾がある。","romaji":"Hanashi ni mujun ga aru.","th":"เรื่องมีจุดขัดแย้ง"}]},{"char":"盾","on":"ジュン","kun":"たて","romaji":"jun / tate","meaning":"โล่","examples":[{"jp":"矛盾だらけです。","romaji":"Mujun darake desu.","th":"ขัดแย้งเต็มไปหมด"},{"jp":"盾に隠れる。","romaji":"Tate ni kakureru.","th":"ซ่อนหลังโล่"},{"jp":"後ろ盾が必要。","romaji":"Ushirodate ga hitsuyou.","th":"ต้องการคนหนุนหลัง"}]},{"char":"煩","on":"ハン","kun":"わずら(う)","romaji":"han / wazura(u)","meaning":"ยุ่งยาก, รบกวน","examples":[{"jp":"煩雑な作業です。","romaji":"Hanzatsu na sagyou desu.","th":"งานยุ่งยาก"},{"jp":"心が煩います。","romaji":"Kokoro ga wazuraimasu.","th":"ใจกังวล"},{"jp":"煩悩を断ちます。","romaji":"Bonnou o tachimasu.","th":"ตัดกิเลส"}]},{"char":"潔","on":"ケツ","kun":"いさぎよ(い)","romaji":"ketsu / isagiyo(i)","meaning":"บริสุทธิ์, สะอาด, กล้าหาญ","examples":[{"jp":"簡潔に話します。","romaji":"Kanketsu ni hanashimasu.","th":"พูดกระชับ"},{"jp":"清潔にしてください。","romaji":"Seiketsu ni shite kudasai.","th":"ทำให้สะอาด"},{"jp":"潔く認めました。","romaji":"Isagiyoku mitomemashita.","th":"ยอมรับอย่างเด็ดเดี่ยว"}]},{"char":"緊","on":"キン","kun":"—","romaji":"kin","meaning":"ตึง, เร่งด่วน","examples":[{"jp":"緊張しています。","romaji":"Kinchou shite imasu.","th":"กำลังตื่นเต้น"},{"jp":"緊急事態です。","romaji":"Kinkyuu jitai desu.","th":"เป็นเหตุฉุกเฉิน"},{"jp":"緊密な関係。","romaji":"Kinmitsu na kankei.","th":"ความสัมพันธ์ใกล้ชิด"}]},{"char":"張","on":"チョウ","kun":"は(る)","romaji":"chou / ha(ru)","meaning":"ขึง, ยืด, ตึง","examples":[{"jp":"緊張する。","romaji":"Kinchou suru.","th":"ตื่นเต้น"},{"jp":"頑張ります。","romaji":"Ganbarimasu.","th":"จะพยายาม"},{"jp":"ロープを張ります。","romaji":"Roopu o harimasu.","th":"ขึงเชือก"}]},{"char":"従","on":"ジュウ","kun":"したが(う)","romaji":"juu / shitaga(u)","meaning":"ปฏิบัติตาม, รอง","examples":[{"jp":"規則に従います。","romaji":"Kisoku ni shitagaimasu.","th":"ปฏิบัติตามกฎ"},{"jp":"従業員です。","romaji":"Juugyouin desu.","th":"เป็นพนักงาน"},{"jp":"従って結果が出ました。","romaji":"Shitagatte kekka ga demashita.","th":"ดังนั้นผลจึงออกมา"}]},{"char":"改","on":"カイ","kun":"あらた(める)","romaji":"kai / arata(meru)","meaning":"เปลี่ยน, แก้","examples":[{"jp":"改善しました。","romaji":"Kaizen shimashita.","th":"ปรับปรุงแล้ว"},{"jp":"態度を改めます。","romaji":"Taido o aratamemasu.","th":"ปรับทัศนคติ"},{"jp":"改札口です。","romaji":"Kaisatsu-guchi desu.","th":"ทางผ่านเก็บตั๋ว"}]},{"char":"善","on":"ゼン","kun":"よ(い)","romaji":"zen / yo(i)","meaning":"ดี, ความดี","examples":[{"jp":"改善が必要です。","romaji":"Kaizen ga hitsuyou desu.","th":"ต้องปรับปรุง"},{"jp":"親善試合です。","romaji":"Shinzen jiai desu.","th":"เป็นเกมกระชับมิตร"},{"jp":"最善を尽くします。","romaji":"Saizen o tsukushimasu.","th":"จะทำให้ดีที่สุด"}]},{"char":"唆","on":"サ","kun":"そそのか(す)","romaji":"sa / sosonoka(su)","meaning":"ยุยง, ชักจูง","examples":[{"jp":"示唆しています。","romaji":"Shisa shite imasu.","th":"บ่งชี้"},{"jp":"示唆に富む話。","romaji":"Shisa ni tomu hanashi.","th":"เรื่องชวนคิด"},{"jp":"教唆罪。","romaji":"Kyousa-zai.","th":"คดียุยง"}]},{"char":"推","on":"スイ","kun":"お(す)","romaji":"sui / o(su)","meaning":"ผลัก, ส่งเสริม","examples":[{"jp":"推進します。","romaji":"Suishin shimasu.","th":"ขับเคลื่อน"},{"jp":"推薦します。","romaji":"Suisen shimasu.","th":"แนะนำ (ให้รางวัล)"},{"jp":"推測ですか。","romaji":"Suisoku desu ka.","th":"เป็นการคาดเดาหรือ"}]},{"char":"維","on":"イ","kun":"—","romaji":"i","meaning":"รักษา, ใย","examples":[{"jp":"維持する。","romaji":"Iji suru.","th":"รักษา"},{"jp":"繊維産業。","romaji":"Sen'i sangyou.","th":"อุตสาหกรรมสิ่งทอ"},{"jp":"維新。","romaji":"Ishin.","th":"การปฏิรูป"}]},{"char":"依","on":"イ","kun":"—","romaji":"i","meaning":"พึ่งพา, ตาม","examples":[{"jp":"依存する。","romaji":"Izon suru.","th":"พึ่งพา"},{"jp":"依頼する。","romaji":"Irai suru.","th":"ขอร้อง"},{"jp":"依然として。","romaji":"Izen to shite.","th":"ยังคง"}]},{"char":"圧","on":"アツ","kun":"—","romaji":"atsu","meaning":"กด, กดดัน","examples":[{"jp":"圧倒的だ。","romaji":"Attou-teki da.","th":"ท่วมท้น"},{"jp":"圧力をかける。","romaji":"Atsuryoku o kakeru.","th":"กดดัน"},{"jp":"血圧を測る。","romaji":"Ketsuatsu o hakaru.","th":"วัดความดัน"}]},{"char":"概","on":"ガイ","kun":"—","romaji":"gai","meaning":"โดยสรุป, รวมๆ","examples":[{"jp":"概念を理解する。","romaji":"Gainen o rikai suru.","th":"เข้าใจแนวคิด"},{"jp":"概要を説明する。","romaji":"Gaiyou o setsumei suru.","th":"อธิบายโดยสรุป"},{"jp":"大概分かった。","romaji":"Taigai wakatta.","th":"เข้าใจเกือบหมด"}]},{"char":"該","on":"ガイ","kun":"—","romaji":"gai","meaning":"ตรงกับ, ดังกล่าว","examples":[{"jp":"該当する。","romaji":"Gaitou suru.","th":"เข้าข่าย"},{"jp":"該当者を探す。","romaji":"Gaitousha o sagasu.","th":"หาผู้ที่เข้าข่าย"},{"jp":"当該問題。","romaji":"Tougai mondai.","th":"ปัญหาดังกล่าว"}]},{"char":"確","on":"カク","kun":"たし(か)","romaji":"kaku / tashi(ka)","meaning":"แน่นอน, ยืนยัน","examples":[{"jp":"確保する。","romaji":"Kakuho suru.","th":"รักษาไว้"},{"jp":"確実に。","romaji":"Kakujitsu ni.","th":"อย่างแน่นอน"},{"jp":"確立する。","romaji":"Kakuritsu suru.","th":"ก่อตั้ง"}]},{"char":"規","on":"キ","kun":"—","romaji":"ki","meaning":"กฎ, มาตรฐาน","examples":[{"jp":"規制する。","romaji":"Kisei suru.","th":"ควบคุม"},{"jp":"規則を守る。","romaji":"Kisoku o mamoru.","th":"ปฏิบัติตามกฎ"},{"jp":"規模が大きい。","romaji":"Kibo ga ookii.","th":"ขนาดใหญ่"}]},{"char":"調","on":"チョウ","kun":"ととの(える)","romaji":"chou / totono(eru)","meaning":"ปรับ, ตรวจ","examples":[{"jp":"調整する。","romaji":"Chousei suru.","th":"ปรับแต่ง"},{"jp":"協調する。","romaji":"Kyouchou suru.","th":"ประสานงาน"},{"jp":"強調する。","romaji":"Kyouchou suru.","th":"เน้น"}]},{"char":"制","on":"セイ","kun":"—","romaji":"sei","meaning":"ควบคุม, ระบบ","examples":[{"jp":"制度を変える。","romaji":"Seido o kaeru.","th":"เปลี่ยนระบบ"},{"jp":"制限する。","romaji":"Seigen suru.","th":"จำกัด"},{"jp":"規制する。","romaji":"Kisei suru.","th":"ควบคุม"}]},{"char":"約","on":"ヤク","kun":"—","romaji":"yaku","meaning":"สัญญา, ประมาณ","examples":[{"jp":"制約がある。","romaji":"Seiyaku ga aru.","th":"มีข้อจำกัด"},{"jp":"約束する。","romaji":"Yakusoku suru.","th":"สัญญา"},{"jp":"約百人。","romaji":"Yaku hyakunin.","th":"ประมาณ 100 คน"}]},{"char":"渉","on":"ショウ","kun":"—","romaji":"shou","meaning":"เกี่ยวข้อง, เจรจา","examples":[{"jp":"交渉する。","romaji":"Koushou suru.","th":"เจรจา"},{"jp":"干渉する。","romaji":"Kanshou suru.","th":"แทรกแซง"},{"jp":"渉外部。","romaji":"Shougai-bu.","th":"แผนกต่างประเทศ"}]},{"char":"端","on":"タン","kun":"はし・はた","romaji":"tan / hashi","meaning":"ปลาย, ขอบ","examples":[{"jp":"極端だ。","romaji":"Kyokutan da.","th":"สุดโต่ง"},{"jp":"端っこ。","romaji":"Hashikko.","th":"ขอบ"},{"jp":"発端になる。","romaji":"Hottan ni naru.","th":"เป็นจุดเริ่มต้น"}]},{"char":"極","on":"キョク","kun":"きわ(める)","romaji":"kyoku / kiwa(meru)","meaning":"สุด, ขั้วโลก","examples":[{"jp":"極端な考え。","romaji":"Kyokutan na kangae.","th":"ความคิดสุดโต่ง"},{"jp":"北極。","romaji":"Hokkyoku.","th":"ขั้วโลกเหนือ"},{"jp":"極めて重要。","romaji":"Kiwamete juuyou.","th":"สำคัญยิ่ง"}]},{"char":"統","on":"トウ","kun":"す(べる)","romaji":"tou / su(beru)","meaning":"รวม, ปกครอง","examples":[{"jp":"統一する。","romaji":"Touitsu suru.","th":"รวมเป็นหนึ่ง"},{"jp":"伝統文化。","romaji":"Dentou bunka.","th":"วัฒนธรรมดั้งเดิม"},{"jp":"大統領。","romaji":"Daitouryou.","th":"ประธานาธิบดี"}]},{"char":"占","on":"セン","kun":"し(める)・うらな(う)","romaji":"sen / shi(meru)","meaning":"ครอง, ทำนาย","examples":[{"jp":"割合を占める。","romaji":"Wariai o shimeru.","th":"ครองสัดส่วน"},{"jp":"占いを信じる。","romaji":"Uranai o shinjiru.","th":"เชื่อดวง"},{"jp":"独占する。","romaji":"Dokusen suru.","th":"ผูกขาด"}]},{"char":"偏","on":"ヘン","kun":"かたよ(る)","romaji":"hen / katayo(ru)","meaning":"เอนเอียง, ลำเอียง","examples":[{"jp":"偏った見方。","romaji":"Katayotta mikata.","th":"มุมมองลำเอียง"},{"jp":"偏見を持つ。","romaji":"Henken o motsu.","th":"มีอคติ"},{"jp":"栄養が偏る。","romaji":"Eiyou ga katayoru.","th":"สารอาหารไม่สมดุล"}]},{"char":"促","on":"ソク","kun":"うなが(す)","romaji":"soku / unaga(su)","meaning":"กระตุ้น, เร่ง","examples":[{"jp":"成長を促す。","romaji":"Seichou o unagasu.","th":"กระตุ้นการเติบโต"},{"jp":"促進する。","romaji":"Sokushin suru.","th":"ส่งเสริม"},{"jp":"催促する。","romaji":"Saisoku suru.","th":"ทวงถาม"}]},{"char":"抑","on":"ヨク","kun":"おさ(える)","romaji":"yoku / osa(eru)","meaning":"กด, ระงับ","examples":[{"jp":"感情を抑える。","romaji":"Kanjou o osaeru.","th":"ระงับอารมณ์"},{"jp":"抑制する。","romaji":"Yokusei suru.","th":"ยับยั้ง"},{"jp":"抑圧する。","romaji":"Yokuatsu suru.","th":"กดดัน"}]},{"char":"膨","on":"ボウ","kun":"ふく(らむ)","romaji":"bou / fuku(ramu)","meaning":"พอง, ขยาย","examples":[{"jp":"膨大な量。","romaji":"Boudai na ryou.","th":"จำนวนมหาศาล"},{"jp":"膨らむ。","romaji":"Fukuramu.","th":"พองขึ้น"},{"jp":"膨張する。","romaji":"Bouchou suru.","th":"ขยายตัว"}]},{"char":"網","on":"モウ","kun":"あみ","romaji":"mou / ami","meaning":"ตาข่าย, ครอบคลุม","examples":[{"jp":"網羅する。","romaji":"Moura suru.","th":"ครอบคลุมทั้งหมด"},{"jp":"インターネット。","romaji":"Intaanetto.","th":"อินเทอร์เน็ต"},{"jp":"通信網。","romaji":"Tsuushin-mou.","th":"เครือข่ายการสื่อสาร"}]}]